CRAPL-LICENSE.txt
MANIFEST.in
setup.cfg
setup.py
honeybadgerbft/__init__.py
honeybadgerbft.egg-info/PKG-INFO
honeybadgerbft.egg-info/SOURCES.txt
honeybadgerbft.egg-info/dependency_links.txt
honeybadgerbft.egg-info/not-zip-safe
honeybadgerbft.egg-info/top_level.txt