Metadata-Version: 1.1
Name: honeybadgerbft
Version: 0.0.0
Summary: The Honey Badger of BFT Protocols
Home-page: https://github.com/amiller/HoneyBadgerBFT
Author: Andrew Miller et al.
Author-email: UNKNOWN
License: CRAPL
Keywords: distributed systems,cryptography,byzantine fault tolerance
Platform: UNKNOWN
Classifier: Development Status :: 1 - Planning
Classifier: Intended Audience :: Developers
Classifier: Natural Language :: English
Classifier: Programming Language :: Python :: 2 :: Only
Classifier: Programming Language :: Python :: 2.7
